Workbook

Sheet Initial Results
A1: All Papers | B1: Erin | C1: Tanim | D1: Reason for Disagreement (E) | E1: Reason for Disagreement (T) | F1: Erin Accepted | G1: Tanim Accepted | J1: Legend:
A2: Preparing medical first responders for crises: a systematic literature review of disaster training programs and their effectiveness | B2: =IF(COUNTIF('Erin Accepted'!B:B, TRIM(SUBSTITUTE(A2, " ", ""))) > 0, "O", "X") -> X | C2: =IF(COUNTIF('Tanim Accepted'!B:B, TRIM(SUBSTITUTE(A2, " ", ""))) > 0, "O", "X") -> O | F2: =COUNTIF(B:B, "O") -> 84 | G2: =COUNTIF(C:C, "O") -> 119 | J2: Accept: O
A3: A Next-Generation Augmented Reality Platform for Mass Casualty Incidents (MCI) | B3: =IF(COUNTIF('Erin Accepted'!B:B, TRIM(SUBSTITUTE(A3, " ", ""))) > 0, "O", "X") -> X | C3: =IF(COUNTIF('Tanim Accepted'!B:B, TRIM(SUBSTITUTE(A3, " ", ""))) > 0, "O", "X") -> O | J3: Reject: X
A4: Ajna: A Wearable Shared Perception System for Extreme Sensemaking | B4: =IF(COUNTIF('Erin Accepted'!B:B, TRIM(SUBSTITUTE(A4, " ", ""))) > 0, "O", "X") -> X | C4: =IF(COUNTIF('Tanim Accepted'!B:B, TRIM(SUBSTITUTE(A4, " ", ""))) > 0, "O", "X") -> O
A5: Leveraging Augmented Reality for Improved Situational Awareness During UAV-Driven Search and Rescue Missions | B5: =IF(COUNTIF('Erin Accepted'!B:B, TRIM(SUBSTITUTE(A5, " ", ""))) > 0, "O", "X") -> X | C5: =IF(COUNTIF('Tanim Accepted'!B:B, TRIM(SUBSTITUTE(A5, " ", ""))) > 0, "O", "X") -> O
A6: Research on the application of AR in the safety inspection of opening and closing stations | B6: =IF(COUNTIF('Erin Accepted'!B:B, TRIM(SUBSTITUTE(A6, " ", ""))) > 0, "O", "X") -> X | C6: =IF(COUNTIF('Tanim Accepted'!B:B, TRIM(SUBSTITUTE(A6, " ", ""))) > 0, "O", "X") -> O
A7: Blaze Buster Augmented Reality Usability Evaluation | B7: =IF(COUNTIF('Erin Accepted'!B:B, TRIM(SUBSTITUTE(A7, " ", ""))) > 0, "O", "X") -> X | C7: =IF(COUNTIF('Tanim Accepted'!B:B, TRIM(SUBSTITUTE(A7, " ", ""))) > 0, "O", "X") -> O
A8: A Fire Reconnaissance Robot Based on SLAM Position, Thermal Imaging Technologies, and AR Display | B8: =IF(COUNTIF('Erin Accepted'!B:B, TRIM(SUBSTITUTE(A8, " ", ""))) > 0, "O", "X") -> X | C8: =IF(COUNTIF('Tanim Accepted'!B:B, TRIM(SUBSTITUTE(A8, " ", ""))) > 0, "O", "X") -> O
A9: Design of a Mixed Reality System for Simulating Indoor Disaster Rescue | B9: =IF(COUNTIF('Erin Accepted'!B:B, TRIM(SUBSTITUTE(A9, " ", ""))) > 0, "O", "X") -> O | C9: =IF(COUNTIF('Tanim Accepted'!B:B, TRIM(SUBSTITUTE(A9, " ", ""))) > 0, "O", "X") -> O
A10: Method and application of information sharing throughout the emergency rescue process based on 5G and AR wearable devices | B10: =IF(COUNTIF('Erin Accepted'!B:B, TRIM(SUBSTITUTE(A10, " ", ""))) > 0, "O", "X") -> O | C10: =IF(COUNTIF('Tanim Accepted'!B:B, TRIM(SUBSTITUTE(A10, " ", ""))) > 0, "O", "X") -> O
A11: Mobile Augmented Reality Techniques for Emergency Response | B11: =IF(COUNTIF('Erin Accepted'!B:B, TRIM(SUBSTITUTE(A11, " ", ""))) > 0, "O", "X") -> O | C11: =IF(COUNTIF('Tanim Accepted'!B:B, TRIM(SUBSTITUTE(A11, " ", ""))) > 0, "O", "X") -> O
A12: Tangible Immersive Trauma Simulation: Is Mixed Reality the next Level of Medical Skills Training? | B12: =IF(COUNTIF('Erin Accepted'!B:B, TRIM(SUBSTITUTE(A12, " ", ""))) > 0, "O", "X") -> X | C12: =IF(COUNTIF('Tanim Accepted'!B:B, TRIM(SUBSTITUTE(A12, " ", ""))) > 0, "O", "X") -> O
A13: Training emergency responders through augmented reality mobile interfaces | B13: =IF(COUNTIF('Erin Accepted'!B:B, TRIM(SUBSTITUTE(A13, " ", ""))) > 0, "O", "X") -> O | C13: =IF(COUNTIF('Tanim Accepted'!B:B, TRIM(SUBSTITUTE(A13, " ", ""))) > 0, "O", "X") -> O
A14: Eliciting Requirements for a Multisensory EXtended Reality Platform for Training and Informal Learning | B14: =IF(COUNTIF('Erin Accepted'!B:B, TRIM(SUBSTITUTE(A14, " ", ""))) > 0, "O", "X") -> X | C14: =IF(COUNTIF('Tanim Accepted'!B:B, TRIM(SUBSTITUTE(A14, " ", ""))) > 0, "O", "X") -> O
A15: Design of Intelligent Firefighter Helmet Based on AR Technology | B15: =IF(COUNTIF('Erin Accepted'!B:B, TRIM(SUBSTITUTE(A15, " ", ""))) > 0, "O", "X") -> O | C15: =IF(COUNTIF('Tanim Accepted'!B:B, TRIM(SUBSTITUTE(A15, " ", ""))) > 0, "O", "X") -> O
... A1752: A Mixed-Methods Approach for the Evaluation of Situational Awareness and User Experience with Augmented Reality Technologies | B1752: =IF(COUNTIF('Erin Accepted'!B:B, TRIM(SUBSTITUTE(A1752, " ", ""))) > 0, "O", "X") -> O | C1752: =IF(COUNTIF('Tanim Accepted'!B:B, TRIM(SUBSTITUTE(A1752, " ", ""))) > 0, "O", "X") -> X

Sheet Erin Accepted
A1: Evaluation of an augmented reality platform for austere surgical telementoring: a randomized controlled crossover study in cricothyroidotomies | B1: =TRIM(SUBSTITUTE(A1," ","")) -> Evaluationofanaugmentedrealityplatformforausteresurgicaltelementoring:arandomizedcontrolledcrossoverstudyincricothyroidotomies
A2: A 'mixed reality' simulator concept for future Medical Emergency Response Team training | B2: =TRIM(SUBSTITUTE(A2," ","")) -> A'mixedreality'simulatorconceptforfutureMedicalEmergencyResponseTeamtraining
A3: An augmented reality system for health care provision via telematics support | B3: =TRIM(SUBSTITUTE(A3," ","")) -> Anaugmentedrealitysystemforhealthcareprovisionviatelematicssupport
A4: Technical support by smart glasses during a mass casualty incident: A randomized controlled simulation trial on technically assisted triage and telemedical app use in disaster medicine | B4: =TRIM(SUBSTITUTE(A4," ","")) -> Technicalsupportbysmartglassesduringamasscasualtyincident:Arandomizedcontrolledsimulationtrialontechnicallyassistedtriageandtelemedicalappuseindisastermedicine
A5: Usability and reliability of smart glasses for secondary triage during mass casualty incidents | B5: =TRIM(SUBSTITUTE(A5," ","")) -> Usabilityandreliabilityofsmartglassesforsecondarytriageduringmasscasualtyincidents
A6: Head-Worn Displays for Emergency Medical Services Staff | B6: =TRIM(SUBSTITUTE(A6," ","")) -> Head-WornDisplaysforEmergencyMedicalServicesStaff
A7: CPR Emergency Assistance Through Mixed Reality Communication | B7: =TRIM(SUBSTITUTE(A7," ","")) -> CPREmergencyAssistanceThroughMixedRealityCommunication
A8: Telementorship in Underway Naval Operations: Leveraging Operational Virtual Health for Tactical Combat Casualty Care | B8: =TRIM(SUBSTITUTE(A8," ","")) -> TelementorshipinUnderwayNavalOperations:LeveragingOperationalVirtualHealthforTacticalCombatCasualtyCare
A9: Augmented Reality Technology to Facilitate Proficiency in Emergency Medical Procedures | B9: =TRIM(SUBSTITUTE(A9," ","")) -> AugmentedRealityTechnologytoFacilitateProficiencyinEmergencyMedicalProcedures
A10: Augmented reality training, command and control framework for first responders | B10: =TRIM(SUBSTITUTE(A10," ","")) -> Augmentedrealitytraining,commandandcontrolframeworkforfirstresponders
A11: Next generation emergency management common operating picture software/systems (COPSS) | B11: =TRIM(SUBSTITUTE(A11," ","")) -> Nextgenerationemergencymanagementcommonoperatingpicturesoftware/systems(COPSS)
A12: Radiological Incident System using Augmented Reality (RISAR) | B12: =TRIM(SUBSTITUTE(A12," ","")) -> RadiologicalIncidentSystemusingAugmentedReality(RISAR)
... A84: Mobile AR Application for Navigation and Emergency Response | B84: =TRIM(SUBSTITUTE(A84," ","")) -> MobileARApplicationforNavigationandEmergencyResponse

Sheet Tanim Accepted
A1: User-CenteredDesignandEvaluationofARTTS:anAugmentedRealityTriageToolSuiteforMassCasualtyIncidents | B1: =TRIM(SUBSTITUTE(A1," ","")) -> User-CenteredDesignandEvaluationofARTTS:anAugmentedRealityTriageToolSuiteforMassCasualtyIncidents
A2: CreatingInformalLearningandFirstResponderTrainingXRExperienceswiththeImmersiveDeck | B2: =TRIM(SUBSTITUTE(A2," ","")) -> CreatingInformalLearningandFirstResponderTrainingXRExperienceswiththeImmersiveDeck
A3: AnAugmentedRealityFrameworkforFirstResponders:theRESPOND-Aprojectapproach | B3: =TRIM(SUBSTITUTE(A3," ","")) -> AnAugmentedRealityFrameworkforFirstResponders:theRESPOND-Aprojectapproach
A4: EnhancingDisasterResponseTrainingthroughImmersiveAR/VRSimulations | B4: =TRIM(SUBSTITUTE(A4," ","")) -> EnhancingDisasterResponseTrainingthroughImmersiveAR/VRSimulations
A5: Demo:CollaborativeMixed-Reality-BasedFirefighterTraining | B5: =TRIM(SUBSTITUTE(A5," ","")) -> Demo:CollaborativeMixed-Reality-BasedFirefighterTraining
A6: TrainandEquipFirefighterswithCognitiveVirtualandAugmentedReality | B6: =TRIM(SUBSTITUTE(A6," ","")) -> TrainandEquipFirefighterswithCognitiveVirtualandAugmentedReality
A7: MiRTE:MixedRealityTriageandEvacuationgameforMassCasualtyinformationsystemsdesign,testingandtraining | B7: =TRIM(SUBSTITUTE(A7," ","")) -> MiRTE:MixedRealityTriageandEvacuationgameforMassCasualtyinformationsystemsdesign,testingandtraining
A8: RedCrossTriageAppDesignforAugmentedRealityGlasses | B8: =TRIM(SUBSTITUTE(A8," ","")) -> RedCrossTriageAppDesignforAugmentedRealityGlasses
A9: VR[weare]Training-WorkshoponCollaborativeVirtualTrainingforChallengingContexts | B9: =TRIM(SUBSTITUTE(A9," ","")) -> VR[weare]Training-WorkshoponCollaborativeVirtualTrainingforChallengingContexts
A10: FirstResponders'TakeonTechnology:ADeepDiveintoMobileandARInterfacePreferences. | B10: =TRIM(SUBSTITUTE(A10," ","")) -> FirstResponders'TakeonTechnology:ADeepDiveintoMobileandARInterfacePreferences.
A11: XRfor FirstResponders:Concepts,Challengesand FuturePotentialof ImmersiveTraining | B11: =TRIM(SUBSTITUTE(A11," ","")) -> XRfor FirstResponders:Concepts,Challengesand FuturePotentialof ImmersiveTraining
A12: SimulatingNext-GenerationUserInterfacesforLawEnforcementTrafficStops | B12: =TRIM(SUBSTITUTE(A12," ","")) -> SimulatingNext-GenerationUserInterfacesforLawEnforcementTrafficStops
... A119: Towards an immersive virtual reality training system for CBRN disaster preparedness | B119: =TRIM(SUBSTITUTE(A119," ","")) -> TowardsanimmersivevirtualrealitytrainingsystemforCBRNdisasterpreparedness

Sheet Discussion Results
A1: All Papers | B1: Erin | C1: Tanim | D1: Agreement | E1: Reason for Disagreement (E) | F1: Reason for Disagreement (T) | G1: Erin Accepted | H1: Tanim Accepted | I1: Final Decision | J1: Final Notes | K1: Legend:
A2: Ajna: A Wearable Shared Perception System for Extreme Sensemaking | B2: Accept | C2: =IF(COUNTIF('Tanim Accepted'!B:B, TRIM(SUBSTITUTE(A2, " ", ""))) > 0, "Accept", "Reject") -> Accept | D2: =B2=C2 -> TRUE | E2: Came to consensus
A3: Leveraging Augmented Reality for Improved Situational Awareness During UAV-Driven Search and Rescue Missions | B3: Accept | C3: =IF(COUNTIF('Tanim Accepted'!B:B, TRIM(SUBSTITUTE(A3, " ", ""))) > 0, "Accept", "Reject") -> Accept | D3: =B3=C3 -> TRUE | E3: Came to consensus
A4: A Fire Reconnaissance Robot Based on SLAM Position, Thermal Imaging Technologies, and AR Display | B4: Accept | C4: =IF(COUNTIF('Tanim Accepted'!B:B, TRIM(SUBSTITUTE(A4, " ", ""))) > 0, "Accept", "Reject") -> Accept | D4: =B4=C4 -> TRUE | E4: Raise for Group Discussion | F4: Raise for Group Discussion | I4: Accept | J4: Paper to be included in final data, elements need to be addressed in paper
A5: Design of a Mixed Reality System for Simulating Indoor Disaster Rescue | B5: =IF(COUNTIF('Erin Accepted'!B:B, TRIM(SUBSTITUTE(A5, " ", ""))) > 0, "Accept", "Reject") -> Accept | C5: =IF(COUNTIF('Tanim Accepted'!B:B, TRIM(SUBSTITUTE(A5, " ", ""))) > 0, "Accept", "Reject") -> Accept | D5: =B5=C5 -> TRUE
A6: Method and application of information sharing throughout the emergency rescue process based on 5G and AR wearable devices | B6: =IF(COUNTIF('Erin Accepted'!B:B, TRIM(SUBSTITUTE(A6, " ", ""))) > 0, "Accept", "Reject") -> Accept | C6: =IF(COUNTIF('Tanim Accepted'!B:B, TRIM(SUBSTITUTE(A6, " ", ""))) > 0, "Accept", "Reject") -> Accept | D6: =B6=C6 -> TRUE
A7: Mobile Augmented Reality Techniques for Emergency Response | B7: =IF(COUNTIF('Erin Accepted'!B:B, TRIM(SUBSTITUTE(A7, " ", ""))) > 0, "Accept", "Reject") -> Accept | C7: =IF(COUNTIF('Tanim Accepted'!B:B, TRIM(SUBSTITUTE(A7, " ", ""))) > 0, "Accept", "Reject") -> Accept | D7: =B7=C7 -> TRUE
A8: Training emergency responders through augmented reality mobile interfaces | B8: =IF(COUNTIF('Erin Accepted'!B:B, TRIM(SUBSTITUTE(A8, " ", ""))) > 0, "Accept", "Reject") -> Accept | C8: =IF(COUNTIF('Tanim Accepted'!B:B, TRIM(SUBSTITUTE(A8, " ", ""))) > 0, "Accept", "Reject") -> Accept | D8: =B8=C8 -> TRUE
A9: Design of Intelligent Firefighter Helmet Based on AR Technology | B9: =IF(COUNTIF('Erin Accepted'!B:B, TRIM(SUBSTITUTE(A9, " ", ""))) > 0, "Accept", "Reject") -> Accept | C9: =IF(COUNTIF('Tanim Accepted'!B:B, TRIM(SUBSTITUTE(A9, " ", ""))) > 0, "Accept", "Reject") -> Accept | D9: =B9=C9 -> TRUE
A10: Exploring the Design Space of Optical See-through AR Head-Mounted Displays to Support First Responders in the Field | B10: =IF(COUNTIF('Erin Accepted'!B:B, TRIM(SUBSTITUTE(A10, " ", ""))) > 0, "Accept", "Reject") -> Accept | C10: =IF(COUNTIF('Tanim Accepted'!B:B, TRIM(SUBSTITUTE(A10, " ", ""))) > 0, "Accept", "Reject") -> Accept | D10: =B10=C10 -> TRUE
A11: Augmented Reality for Real-time Decision-Making in Flood Emergencies | B11: Accept | C11: =IF(COUNTIF('Tanim Accepted'!B:B, TRIM(SUBSTITUTE(A11, " ", ""))) > 0, "Accept", "Reject") -> Accept | D11: =B11=C11 -> TRUE | E11: Came to consensus | F11: POI, water control, real time maps interfaces
A12: See through the Fire: Evaluating the Augmentation of Visual Perception of Firefighters Using Depth and Thermal Cameras | B12: Accept | C12: Accept | D12: =B12=C12 -> TRUE | E12: Tanim and I discussed; I do not remember the results of the discussion or why this is still marked as accepted. Did we mean to reject? The paper provides no context for interfaces developed -- only thermal and depth camera output. | F12: Related but no actual evidence of showing any results or demo
A13: AR Browser for Points of Interest in Disaster Response in UAV Imagery | B13: =IF(COUNTIF('Erin Accepted'!B:B, TRIM(SUBSTITUTE(A13, " ", ""))) > 0, "Accept", "Reject") -> Accept | C13: =IF(COUNTIF('Tanim Accepted'!B:B, TRIM(SUBSTITUTE(A13, " ", ""))) > 0, "Accept", "Reject") -> Accept | D13: =B13=C13 -> TRUE
A14: A Virtual and Augmented Reality Platform for the Training of First Responders of the Ambulance Bus | B14: Accept | C14: =IF(COUNTIF('Tanim Accepted'!B:B, TRIM(SUBSTITUTE(A14, " ", ""))) > 0, "Accept", "Reject") -> Accept | D14: =B14=C14 -> TRUE | E14: We have discussed previously, consensus was no as no interfaces developed for training in this paper were proposed for field | F14: Interactive training scenario, may need discussion | I14: Accept | J14: Paper to be included in final data, elements need to be addressed in paper
A15: SidebARs: Improving Awareness of off-Screen Elements in Mobile Augmented Reality | B15: =IF(COUNTIF('Erin Accepted'!B:B, TRIM(SUBSTITUTE(A15, " ", ""))) > 0, "Accept", "Reject") -> Accept | C15: =IF(COUNTIF('Tanim Accepted'!B:B, TRIM(SUBSTITUTE(A15, " ", ""))) > 0, "Accept", "Reject") -> Accept | D15: =B15=C15 -> TRUE
A16: A 'mixed reality' simulator concept for future Medical Emergency Response Team training | B16: =IF(COUNTIF('Erin Accepted'!B:B, TRIM(SUBSTITUTE(A16, " ", ""))) > 0, "Accept", "Reject") -> Accept | C16: =IF(COUNTIF('Tanim Accepted'!B:B, TRIM(SUBSTITUTE(A16, " ", ""))) > 0, "Accept", "Reject") -> Accept | D16: =B16=C16 -> TRUE
A17: Supporting first responder in-field communication and navigation using head-mounted displays | B17: =IF(COUNTIF('Erin Accepted'!B:B, TRIM(SUBSTITUTE(A17, " ", ""))) > 0, "Accept", "Reject") -> Accept | C17: =IF(COUNTIF('Tanim Accepted'!B:B, TRIM(SUBSTITUTE(A17, " ", ""))) > 0, "Accept", "Reject") -> Accept | D17: =B17=C17 -> TRUE
A18: Juxtopia®CAMMRAD Prepare: A Wearable AI-AR Platform for Clinical Training Emergency First Response Teams | B18: Accept | C18: =IF(COUNTIF('Tanim Accepted'!B:B, TRIM(SUBSTITUTE(A18, " ", ""))) > 0, "Accept", "Reject") -> Accept | D18: =B18=C18 -> TRUE | F18: Interactable training interface, might need discussion | I18: Accept | J18: Original review identified AIVR submission, include the SVR version instead
A19: Prehospital Pediatric Emergency Training Using Augmented Reality Simulation: A Prospective, Mixed Methods Study | B19: Accept | C19: =IF(COUNTIF('Tanim Accepted'!B:B, TRIM(SUBSTITUTE(A19, " ", ""))) > 0, "Accept", "Reject") -> Accept | D19: =B19=C19 -> TRUE | F19: Might need to discuss | I19: Accept | J19: Ensure the representation of training simulation in the final paper.
A20: Evaluation of an augmented reality platform for austere surgical telementoring: a randomized controlled crossover study in cricothyroidotomies | B20: =IF(COUNTIF('Erin Accepted'!B:B, TRIM(SUBSTITUTE(A20, " ", ""))) > 0, "Accept", "Reject") -> Accept | C20: =IF(COUNTIF('Tanim Accepted'!B:B, TRIM(SUBSTITUTE(A20, " ", ""))) > 0, "Accept", "Reject") -> Accept | D20: =B20=C20 -> TRUE
A21: Augmented reality and training for airway management procedures | B21: =IF(COUNTIF('Erin Accepted'!B:B, TRIM(SUBSTITUTE(A21, " ", ""))) > 0, "Accept", "Reject") -> Accept | C21: =IF(COUNTIF('Tanim Accepted'!B:B, TRIM(SUBSTITUTE(A21, " ", ""))) > 0, "Accept", "Reject") -> Accept | D21: =B21=C21 -> TRUE
A22: Augmented reality points of interest for improved first responder situational awareness | B22: =IF(COUNTIF('Erin Accepted'!B:B, TRIM(SUBSTITUTE(A22, " ", ""))) > 0, "Accept", "Reject") -> Accept | C22: =IF(COUNTIF('Tanim Accepted'!B:B, TRIM(SUBSTITUTE(A22, " ", ""))) > 0, "Accept", "Reject") -> Accept | D22: =B22=C22 -> TRUE
A23: Viability of Augmented Content for Field Policing | B23: =IF(COUNTIF('Erin Accepted'!B:B, TRIM(SUBSTITUTE(A23, " ", ""))) > 0, "Accept", "Reject") -> Accept | C23: =IF(COUNTIF('Tanim Accepted'!B:B, TRIM(SUBSTITUTE(A23, " ", ""))) > 0, "Accept", "Reject") -> Accept | D23: =B23=C23 -> TRUE
A24: Augmented reality based criminal investigation system (ARCRIME) | B24: =IF(COUNTIF('Erin Accepted'!B:B, TRIM(SUBSTITUTE(A24, " ", ""))) > 0, "Accept", "Reject") -> Accept | C24: =IF(COUNTIF('Tanim Accepted'!B:B, TRIM(SUBSTITUTE(A24, " ", ""))) > 0, "Accept", "Reject") -> Accept | D24: =B24=C24 -> TRUE
A25: Mixed Reality for Post-Disaster Situational Awareness | B25: =IF(COUNTIF('Erin Accepted'!B:B, TRIM(SUBSTITUTE(A25, " ", ""))) > 0, "Accept", "Reject") -> Accept | C25: =IF(COUNTIF('Tanim Accepted'!B:B, TRIM(SUBSTITUTE(A25, " ", ""))) > 0, "Accept", "Reject") -> Accept | D25: =B25=C25 -> TRUE
A26: Human-in-the-Loop Robot-Augmented Intelligent System for Emergency Reconnaissance | B26: =IF(COUNTIF('Erin Accepted'!B:B, TRIM(SUBSTITUTE(A26, " ", ""))) > 0, "Accept", "Reject") -> Accept | C26: =IF(COUNTIF('Tanim Accepted'!B:B, TRIM(SUBSTITUTE(A26, " ", ""))) > 0, "Accept", "Reject") -> Accept | D26: =B26=C26 -> TRUE
A27: Object detection and augmented reality annotations for increased situational awareness in light smoke conditions | B27: =IF(COUNTIF('Erin Accepted'!B:B, TRIM(SUBSTITUTE(A27, " ", ""))) > 0, "Accept", "Reject") -> Accept | C27: =IF(COUNTIF('Tanim Accepted'!B:B, TRIM(SUBSTITUTE(A27, " ", ""))) > 0, "Accept", "Reject") -> Accept | D27: =B27=C27 -> TRUE
A28: Real-Time Adaptation of Con-Aware Intelligent User Interfaces, for Enhanced Situational Awareness | B28: Reject | C28: Reject | D28: =B28=C28 -> TRUE | E28: Duplicated | F28: Duplicated | J28: Duplicated, remove this row from final results and keep original hit
A29: Augmented reality in law enforcement from an EU data protection law perspective: The darlene project as a case study | B29: Accept | C29: =IF(COUNTIF('Tanim Accepted'!B:B, TRIM(SUBSTITUTE(A29, " ", ""))) > 0, "Accept", "Reject") -> Accept | D29: =B29=C29 -> TRUE
A30: Seeing through Disaster Rubble in 3D with Ground-Penetrating Radar and Interactive Augmented Reality for Urban Search and Rescue | B30: =IF(COUNTIF('Erin Accepted'!B:B, TRIM(SUBSTITUTE(A30, " ", ""))) > 0, "Accept", "Reject") -> Accept | C30: =IF(COUNTIF('Tanim Accepted'!B:B, TRIM(SUBSTITUTE(A30, " ", ""))) > 0, "Accept", "Reject") -> Accept | D30: =B30=C30 -> TRUE
A31: Implementing user-centered methods and virtual reality to rapidly prototype augmented reality tools for firefighters | B31: =IF(COUNTIF('Erin Accepted'!B:B, TRIM(SUBSTITUTE(A31, " ", ""))) > 0, "Accept", "Reject") -> Accept | C31: =IF(COUNTIF('Tanim Accepted'!B:B, TRIM(SUBSTITUTE(A31, " ", ""))) > 0, "Accept", "Reject") -> Accept | D31: =B31=C31 -> TRUE
A32: An augmented reality application to support deployed emergency teams | B32: =IF(COUNTIF('Erin Accepted'!B:B, TRIM(SUBSTITUTE(A32, " ", ""))) > 0, "Accept", "Reject") -> Accept | C32: =IF(COUNTIF('Tanim Accepted'!B:B, TRIM(SUBSTITUTE(A32, " ", ""))) > 0, "Accept", "Reject") -> Accept | D32: =B32=C32 -> TRUE
A33: CPR Emergency Assistance Through Mixed Reality Communication | B33: =IF(COUNTIF('Erin Accepted'!B:B, TRIM(SUBSTITUTE(A33, " ", ""))) > 0, "Accept", "Reject") -> Accept | C33: =IF(COUNTIF('Tanim Accepted'!B:B, TRIM(SUBSTITUTE(A33, " ", ""))) > 0, "Accept", "Reject") -> Accept | D33: =B33=C33 -> TRUE
A34: Training and supporting first responders by mixed reality environments | B34: =IF(COUNTIF('Erin Accepted'!B:B, TRIM(SUBSTITUTE(A34, " ", ""))) > 0, "Accept", "Reject") -> Accept | C34: =IF(COUNTIF('Tanim Accepted'!B:B, TRIM(SUBSTITUTE(A34, " ", ""))) > 0, "Accept", "Reject") -> Accept | D34: =B34=C34 -> TRUE
A35: Augmented Reality Interface for Adverse-Visibility Conditions Validated by First Responders in Rescue Training Scenarios | B35: Accept | C35: Accept | D35: =B35=C35 -> TRUE | F35: Related to topic with interfaces and thermal camera feedback for data rendering
A36: Augmented Reality in Support of Disaster Response | B36: =IF(COUNTIF('Erin Accepted'!B:B, TRIM(SUBSTITUTE(A36, " ", ""))) > 0, "Accept", "Reject") -> Accept | C36: =IF(COUNTIF('Tanim Accepted'!B:B, TRIM(SUBSTITUTE(A36, " ", ""))) > 0, "Accept", "Reject") -> Accept | D36: =B36=C36 -> TRUE
A37: Single-handed gesture UAV control and video feed AR visualization for first responders | B37: =IF(COUNTIF('Erin Accepted'!B:B, TRIM(SUBSTITUTE(A37, " ", ""))) > 0, "Accept", "Reject") -> Accept | C37: =IF(COUNTIF('Tanim Accepted'!B:B, TRIM(SUBSTITUTE(A37, " ", ""))) > 0, "Accept", "Reject") -> Accept | D37: =B37=C37 -> TRUE
A38: An augmented reality system for health care provision via telematics support | B38: =IF(COUNTIF('Erin Accepted'!B:B, TRIM(SUBSTITUTE(A38, " ", ""))) > 0, "Accept", "Reject") -> Accept | C38: =IF(COUNTIF('Tanim Accepted'!B:B, TRIM(SUBSTITUTE(A38, " ", ""))) > 0, "Accept", "Reject") -> Accept | D38: =B38=C38 -> TRUE
A39: A robotic augmented reality virtual window for law enforcement operations | B39: =IF(COUNTIF('Erin Accepted'!B:B, TRIM(SUBSTITUTE(A39, " ", ""))) > 0, "Accept", "Reject") -> Accept | C39: =IF(COUNTIF('Tanim Accepted'!B:B, TRIM(SUBSTITUTE(A39, " ", ""))) > 0, "Accept", "Reject") -> Accept | D39: =B39=C39 -> TRUE
A40: Augmented Reality Technology to Facilitate Proficiency in Emergency Medical Procedures | B40: =IF(COUNTIF('Erin Accepted'!B:B, TRIM(SUBSTITUTE(A40, " ", ""))) > 0, "Accept", "Reject") -> Accept | C40: =IF(COUNTIF('Tanim Accepted'!B:B, TRIM(SUBSTITUTE(A40, " ", ""))) > 0, "Accept", "Reject") -> Accept | D40: =B40=C40 -> TRUE
A41: 3D Building Reconstruction and Thermal Mapping in Fire Brigade Operations | B41: =IF(COUNTIF('Erin Accepted'!B:B, TRIM(SUBSTITUTE(A41, " ", ""))) > 0, "Accept", "Reject") -> Accept | C41: Accept | D41: =B41=C41 -> TRUE | E41: Ensure correct discussion of data point in SLR | F41: We talked about this earlier and I come to consensus | J41: Data point currently not discussed in SLR; The plan is to discuss how Thermal Imaging aids in S&R scenarios. This pairs nicely with SLAM robot paper
A42: Mobile augmented reality in support of building damage and safety assessment | B42: =IF(COUNTIF('Erin Accepted'!B:B, TRIM(SUBSTITUTE(A42, " ", ""))) > 0, "Accept", "Reject") -> Accept | C42: Accept | D42: =B42=C42 -> TRUE | E42: Through iterative discussion we decided that this paper is being proposed for FRs and is a visual interface with operational merit | F42: Came to consensus
A43: Usability and reliability of smart glasses for secondary triage during mass casualty incidents | B43: =IF(COUNTIF('Erin Accepted'!B:B, TRIM(SUBSTITUTE(A43, " ", ""))) > 0, "Accept", "Reject") -> Accept | C43: Accept | D43: =B43=C43 -> TRUE | E43: Related | F43: Secondary triage | I43: Accept | J43: Ensure representation is correct in final edit
A44: Augmented Reality Farm MAPPER Development: Lessons Learned from an App Designed to Improve Rural Emergency Response | B44: =IF(COUNTIF('Erin Accepted'!B:B, TRIM(SUBSTITUTE(A44, " ", ""))) > 0, "Accept", "Reject") -> Accept | C44: Accept | D44: =B44=C44 -> TRUE | E44: Related | F44: Initially I was skeptical but after several discussions I come to consensus
A45: Google glass for public safety: Leveraging Google Glass for automatic information retrieval and notification by public safety officers in the field | B45: =IF(COUNTIF('Erin Accepted'!B:B, TRIM(SUBSTITUTE(A45, " ", ""))) > 0, "Accept", "Reject") -> Accept | C45: Accept | D45: =B45=C45 -> TRUE | E45: Related | F45: Came to consensus
A46: Technical support by smart glasses during a mass casualty incident: A randomized controlled simulation trial on technically assisted triage and telemedical app use in disaster medicine | B46: =IF(COUNTIF('Erin Accepted'!B:B, TRIM(SUBSTITUTE(A46, " ", ""))) > 0, "Accept", "Reject") -> Accept | C46: Accept | D46: =B46=C46 -> TRUE | E46: Related | F46: Came to consensus
A47: Augmenting situational awareness for first responders using social media as a sensor | B47: =IF(COUNTIF('Erin Accepted'!B:B, TRIM(SUBSTITUTE(A47, " ", ""))) > 0, "Accept", "Reject") -> Accept | C47: Accept | D47: =B47=C47 -> TRUE | E47: Needs further discussion | F47: "Needs further discussion" - Agreed
A48: SimRad.NBC - Simulation and information system for rescue units at CBRN disasters | B48: =IF(COUNTIF('Erin Accepted'!B:B, TRIM(SUBSTITUTE(A48, " ", ""))) > 0, "Accept", "Reject") -> Accept | C48: Accept | D48: =B48=C48 -> TRUE | E48: Through iterative discussion we decided that this paper is being proposed for FRs and is a visual interface with operational merit | F48: Need to discuss with Erin
A49: RoboCup-Rescue: An international cooperative research project of robotics and AI for the disaster mitigation problem | B49: =IF(COUNTIF('Erin Accepted'!B:B, TRIM(SUBSTITUTE(A49, " ", ""))) > 0, "Accept", "Reject") -> Accept | C49: Accept | D49: =B49=C49 -> TRUE | E49: Through iterative discussion we decided that this paper is being proposed for FRs and is a visual interface with operational merit | F49: Need to discuss with Erin
A50: Comparing Firefighters' Perceived Workload Using 2D vs. 3D Building Plans to Support Emergency Response Preplanning in a Simulated Fire Scenario | B50: =IF(COUNTIF('Erin Accepted'!B:B, TRIM(SUBSTITUTE(A50, " ", ""))) > 0, "Accept", "Reject") -> Accept | C50: Accept | D50: =B50=C50 -> TRUE | E50: Through iterative discussion we decided that this paper is being proposed for FRs and is a visual interface with operational merit | F50: Need to discuss with Erin
A51: User-Centered Design and Evaluation of ARTTS: an Augmented Reality Triage Tool Suite for Mass Casualty Incidents | B51: =IF(COUNTIF('Erin Accepted'!B:B, TRIM(SUBSTITUTE(A51, " ", ""))) > 0, "Accept", "Reject") -> Accept | C51: =IF(COUNTIF('Tanim Accepted'!B:B, TRIM(SUBSTITUTE(A51, " ", ""))) > 0, "Accept", "Reject") -> Accept | D51: =B51=C51 -> TRUE
A52: An Augmented Reality Framework for First Responders: the RESPOND-A projectapproach | B52: =IF(COUNTIF('Erin Accepted'!B:B, TRIM(SUBSTITUTE(A52, " ", ""))) > 0, "Accept", "Reject") -> Accept | C52: =IF(COUNTIF('Tanim Accepted'!B:B, TRIM(SUBSTITUTE(A52, " ", ""))) > 0, "Accept", "Reject") -> Accept | D52: =B52=C52 -> TRUE
A53: Augmented card system based on knowledge for medical emergency assistance | B53: =IF(COUNTIF('Erin Accepted'!B:B, TRIM(SUBSTITUTE(A53, " ", ""))) > 0, "Accept", "Reject") -> Accept | C53: Accept | D53: =B53=C53 -> TRUE | E53: Related | F53: Came to consensus
A54: A communication and multi-sensor solution to support dynamic generation of asituational picture | B54: =IF(COUNTIF('Erin Accepted'!B:B, TRIM(SUBSTITUTE(A54, " ", ""))) > 0, "Accept", "Reject") -> Accept | C54: Accept | D54: =B54=C54 -> TRUE | E54: Related | F54: Came to consensus
A55: A Comparative Study of Rendering Devices for Safety-Critical Applications in Operative Control Rooms | B55: =IF(COUNTIF('Erin Accepted'!B:B, TRIM(SUBSTITUTE(A55, " ", ""))) > 0, "Accept", "Reject") -> Accept | C55: Accept | D55: =B55=C55 -> TRUE | E55: Related | F55: Came to consensus
A56: A real-time wearable AR system for egocentric vision on the edge | B56: =IF(COUNTIF('Erin Accepted'!B:B, TRIM(SUBSTITUTE(A56, " ", ""))) > 0, "Accept", "Reject") -> Accept | C56: Accept | D56: =B56=C56 -> TRUE | E56: Related | F56: Came to consensus
A57: Red Cross Triage App Design for Augmented Reality Glasses | B57: Accept | C57: =IF(COUNTIF('Tanim Accepted'!B:B, TRIM(SUBSTITUTE(A57, " ", ""))) > 0, "Accept", "Reject") -> Accept | D57: =B57=C57 -> TRUE | F57: Training interface
A58: Situational Awareness-based Augmented Reality Instructional (ARI) Module for Building Evacuation | B58: =IF(COUNTIF('Erin Accepted'!B:B, TRIM(SUBSTITUTE(A58, " ", ""))) > 0, "Accept", "Reject") -> Accept | C58: Accept | D58: =B58=C58 -> TRUE | E58: Related | F58: Came to consensus
A59: Effective Navigation for an Emergency Response for Firefighters with Wearable Haptic Displays Design | B59: =IF(COUNTIF('Erin Accepted'!B:B, TRIM(SUBSTITUTE(A59, " ", ""))) > 0, "Accept", "Reject") -> Accept | C59: Accept | D59: =B59=C59 -> TRUE | E59: Related | F59: Came to consensus
A60: Mobile AR Application for Navigation and Emergency Response | B60: =IF(COUNTIF('Erin Accepted'!B:B, TRIM(SUBSTITUTE(A60, " ", ""))) > 0, "Accept", "Reject") -> Accept | C60: Accept | D60: =B60=C60 -> TRUE | E60: Related | F60: Came to consensus
A61: Design and simulation of next-generation augmented reality user interfaces invirtual reality | B61: =IF(COUNTIF('Erin Accepted'!B:B, TRIM(SUBSTITUTE(A61, " ", ""))) > 0, "Accept", "Reject") -> Accept | C61: Accept | D61: =B61=C61 -> TRUE | E61: Related | F61: Came to consensus
A62: Mobile Incident Command Dashboard (MIS-D) | B62: =IF(COUNTIF('Erin Accepted'!B:B, TRIM(SUBSTITUTE(A62, " ", ""))) > 0, "Accept", "Reject") -> Accept | C62: Accept | D62: =B62=C62 -> TRUE | E62: Related | F62: Came to consensus
A63: A Mixed Reality Supervision and Telepresence Interface for Outdoor FieldRobotics | B63: =IF(COUNTIF('Erin Accepted'!B:B, TRIM(SUBSTITUTE(A63, " ", ""))) > 0, "Accept", "Reject") -> Accept | C63: Accept | D63: =B63=C63 -> TRUE | E63: Related | F63: Came to consensus
A64: Underground mine emergency evacuation planning: AR implementation and casestudy | B64: =IF(COUNTIF('Erin Accepted'!B:B, TRIM(SUBSTITUTE(A64, " ", ""))) > 0, "Accept", "Reject") -> Accept | C64: Accept | D64: =B64=C64 -> TRUE | E64: Related | F64: Came to consensus
A65: Effects of Augmented Reality-Based Remote Mentoring on Task Performance andCommunication: A Simulation Study in the Context of Emergency MedicalServices | B65: =IF(COUNTIF('Erin Accepted'!B:B, TRIM(SUBSTITUTE(A65, " ", ""))) > 0, "Accept", "Reject") -> Accept | C65: Accept | D65: =B65=C65 -> TRUE | E65: Related | F65: Came to consensus
A66: Using AR to support cross-organisational collaboration in dynamic tasks | B66: =IF(COUNTIF('Erin Accepted'!B:B, TRIM(SUBSTITUTE(A66, " ", ""))) > 0, "Accept", "Reject") -> Accept | C66: Accept | D66: =B66=C66 -> TRUE | E66: Related | F66: Came to consensus
A67: CELIDON: Supporting first responders through 3D AOA-based UWB Ad-hoclocalization | B67: =IF(COUNTIF('Erin Accepted'!B:B, TRIM(SUBSTITUTE(A67, " ", ""))) > 0, "Accept", "Reject") -> Accept | C67: Accept | D67: =B67=C67 -> TRUE | E67: Related | F67: Came to consensus
A68: Optical head-mounted displays in mass casualty incidents: Keeping an eye onpatients and hazardous materials | B68: =IF(COUNTIF('Erin Accepted'!B:B, TRIM(SUBSTITUTE(A68, " ", ""))) > 0, "Accept", "Reject") -> Accept | C68: Accept | D68: =B68=C68 -> TRUE | E68: Related | F68: Came to consensus
A69: A cloud-based fire safety system for emergency responders and civic community | B69: =IF(COUNTIF('Erin Accepted'!B:B, TRIM(SUBSTITUTE(A69, " ", ""))) > 0, "Accept", "Reject") -> Accept | C69: Accept | D69: =B69=C69 -> TRUE | E69: Related | F69: Came to consensus
... A72: Radiological Incident System using Augmented Reality (RISAR) | B72: =IF(COUNTIF('Erin Accepted'!B:B, TRIM(SUBSTITUTE(A72, " ", ""))) > 0, "Accept", "Reject") -> Accept | C72: Accept | D72: =B72=C72 -> TRUE | E72: Related | F72: Came to consensus
A73: Simulating Next-Generation User Interfaces for Law Enforcement Traffic Stops | B73: =IF(COUNTIF('Erin Accepted'!B:B, TRIM(SUBSTITUTE(A73, " ", ""))) > 0, "Accept", "Reject") -> Accept | C73: =IF(COUNTIF('Tanim Accepted'!B:B, TRIM(SUBSTITUTE(A73, " ", ""))) > 0, "Accept", "Reject") -> Accept | D73: =B73=C73 -> TRUE
A74: ERWear: Wearable System Design through the Lens of First Responders | B74: =IF(COUNTIF('Erin Accepted'!B:B, TRIM(SUBSTITUTE(A74, " ", ""))) > 0, "Accept", "Reject") -> Accept | C74: Accept | D74: =B74=C74 -> TRUE | E74: Related | F74: Came to consensus
A75: Person-of-interest detection system using cloud-supported computerized-eyewear | B75: =IF(COUNTIF('Erin Accepted'!B:B, TRIM(SUBSTITUTE(A75, " ", ""))) > 0, "Accept", "Reject") -> Accept | C75: Accept | D75: =B75=C75 -> TRUE | E75: Related | F75: Came to consensus
A76: A ‘mixed reality’ simulator concept for future medical emergency response team training | B76: Reject | C76: Reject | D76: =B76=C76 -> TRUE | E76: Duplicated | F76: Duplicated | J76: Already discussed in SLR and data point in paper. Duplicated? Double check for original accept.
A77: An embedded deep learning system for augmented reality in firefighting applications | B77: =IF(COUNTIF('Erin Accepted'!B:B, TRIM(SUBSTITUTE(A77, " ", ""))) > 0, "Accept", "Reject") -> Accept | C77: Accept | D77: =B77=C77 -> TRUE | E77: Related | F77: Came to consensus
A78: New emergency medicine paradigm via augmented telemedicine | B78: =IF(COUNTIF('Erin Accepted'!B:B, TRIM(SUBSTITUTE(A78, " ", ""))) > 0, "Accept", "Reject") -> Accept | C78: Accept | D78: =B78=C78 -> TRUE | E78: Related | F78: Came to consensus
A79: The what, why and how of achieving urban telepresence | B79: =IF(COUNTIF('Erin Accepted'!B:B, TRIM(SUBSTITUTE(A79, " ", ""))) > 0, "Accept", "Reject") -> Accept | C79: Accept | D79: =B79=C79 -> TRUE | E79: Related | F79: Came to consensus
A80: Collision Avoidance Head-Up Display: Design Considerations for Emergency Services’ Vehicles | B80: =IF(COUNTIF('Erin Accepted'!B:B, TRIM(SUBSTITUTE(A80, " ", ""))) > 0, "Accept", "Reject") -> Accept | C80: Accept | D80: =B80=C80 -> TRUE | E80: Related | F80: Came to consensus
A81: The MagicBook Revisited | B81: =IF(COUNTIF('Erin Accepted'!B:B, TRIM(SUBSTITUTE(A81, " ", ""))) > 0, "Accept", "Reject") -> Accept | C81: Accept | D81: =B81=C81 -> TRUE | E81: Related | F81: Came to consensus
A82: Smart Helmet: Combining Sensors, AI, Augmented Reality, and PersonalProtection to Enhance First Responders' Situational Awareness | B82: Accept | C82: =IF(COUNTIF('Tanim Accepted'!B:B, TRIM(SUBSTITUTE(A82, " ", ""))) > 0, "Accept", "Reject") -> Accept | D82: =B82=C82 -> TRUE | F82: Need to dicuss, I feel like its related | I82: Accept | J82: New Paper, add to data set
A83: Pathfinding for Disaster Emergency Route Using Sparse A* and Dijkstra Algorithm with Augmented Reality | B83: =IF(COUNTIF('Erin Accepted'!B:B, TRIM(SUBSTITUTE(A83, " ", ""))) > 0, "Accept", "Reject") -> Accept | C83: =IF(COUNTIF('Tanim Accepted'!B:B, TRIM(SUBSTITUTE(A83, " ", ""))) > 0, "Accept", "Reject") -> Accept | D83: =B83=C83 -> TRUE
A84: A 5G-Based eHealth Monitoring and Emergency Response System: Experience and Lessons Learned | B84: =IF(COUNTIF('Erin Accepted'!B:B, TRIM(SUBSTITUTE(A84, " ", ""))) > 0, "Accept", "Reject") -> Accept | C84: Accept | D84: =B84=C84 -> TRUE | E84: Related | F84: Came to consensus
A85: Next generation emergency management common operating picture software/systems (COPSS) | B85: =IF(COUNTIF('Erin Accepted'!B:B, TRIM(SUBSTITUTE(A85, " ", ""))) > 0, "Accept", "Reject") -> Accept | C85: Accept | D85: =B85=C85 -> TRUE | E85: Related | F85: Came to consensus
A86: Augmented reality training, command and control framework for firstresponders | B86: =IF(COUNTIF('Erin Accepted'!B:B, TRIM(SUBSTITUTE(A86, " ", ""))) > 0, "Accept", "Reject") -> Accept | C86: =IF(COUNTIF('Tanim Accepted'!B:B, TRIM(SUBSTITUTE(A86, " ", ""))) > 0, "Accept", "Reject") -> Accept | D86: =B86=C86 -> TRUE
A87: A Mixed-Methods Approach for the Evaluation of Situational Awareness and UserExperience with Augmented Reality Technologies | B87: =IF(COUNTIF('Erin Accepted'!B:B, TRIM(SUBSTITUTE(A87, " ", ""))) > 0, "Accept", "Reject") -> Accept | C87: Accept | D87: =B87=C87 -> TRUE | E87: Related | F87: Came to consensus
A88: Guiding Gaze: Comparing Cues for Visual Search | B88: =IF(COUNTIF('Erin Accepted'!B:B, TRIM(SUBSTITUTE(A88, " ", ""))) > 0, "Accept", "Reject") -> Accept | C88: Accept | D88: =B88=C88 -> TRUE | E88: Related | F88: Came to consensus
A89: AR Crew Rescue Assistant and AR Passenger Assistant Application for emergency scenarios on large passenger ships | B89: =IF(COUNTIF('Erin Accepted'!B:B, TRIM(SUBSTITUTE(A89, " ", ""))) > 0, "Accept", "Reject") -> Accept | C89: Accept | D89: =B89=C89 -> TRUE | E89: Related | F89: Came to consensus
A90: Health-5G: A Mixed Reality-Based System for Remote Medical Assistance in Emergency Situations | B90: =IF(COUNTIF('Erin Accepted'!B:B, TRIM(SUBSTITUTE(A90, " ", ""))) > 0, "Accept", "Reject") -> Accept | C90: Accept | D90: =B90=C90 -> TRUE | E90: Related | F90: Came to consensus
A91: Designing for Mobile and Immersive Visual Analytics in the Field | B91: =IF(COUNTIF('Erin Accepted'!B:B, TRIM(SUBSTITUTE(A91, " ", ""))) > 0, "Accept", "Reject") -> Accept | C91: Accept | D91: =B91=C91 -> TRUE | E91: Related | F91: Came to consensus
A92: Real-Time Adaptation of Context-Aware Intelligent User Interfaces, for Enhanced Situational Awareness | B92: =IF(COUNTIF('Erin Accepted'!B:B, TRIM(SUBSTITUTE(A92, " ", ""))) > 0, "Accept", "Reject") -> Accept | C92: Accept | D92: =B92=C92 -> TRUE | E92: Related | F92: Came to consensus
A93: Cross-Device Augmented Reality Systems for Fire and Rescue based on Thermal Imaging and Live Tracking | B93: =IF(COUNTIF('Erin Accepted'!B:B, TRIM(SUBSTITUTE(A93, " ", ""))) > 0, "Accept", "Reject") -> Accept | C93: =IF(COUNTIF('Tanim Accepted'!B:B, TRIM(SUBSTITUTE(A93, " ", ""))) > 0, "Accept", "Reject") -> Accept | D93: =B93=C93 -> TRUE
A94: White Paper on Adaptive Situational Awareness Enhancing Augmented Reality Interface Design on First Responders in Rescue Tasks | B94: Accept | C94: =IF(COUNTIF('Tanim Accepted'!B:B, TRIM(SUBSTITUTE(A94, " ", ""))) > 0, "Accept", "Reject") -> Accept | D94: =B94=C94 -> TRUE | E94: Folloup work from a previous paper | F94: Folloup work from a previous paper
A95: A Mixed-Methods Approach for the Evaluation of Situational Awareness and User Experience with Augmented Reality Technologies | B95: =IF(COUNTIF('Erin Accepted'!B:B, TRIM(SUBSTITUTE(A95, " ", ""))) > 0, "Accept", "Reject") -> Accept | C95: Accept | D95: =B95=C95 -> TRUE | E95: Related | F95: Came to consensus
A96: Preparing medical first responders for crises: a systematic literature review of disaster training programs and their effectiveness | B96: =IF(COUNTIF('Erin Accepted'!B:B, TRIM(SUBSTITUTE(A96, " ", ""))) > 0, "Accept", "Reject") -> Reject | C96: Reject | D96: =B96=C96 -> TRUE | E96: SLR | F96: Came to consensus | G96: =COUNTIF(B:B, "O") -> 0 | H96: =COUNTIF(C:C, "O") -> 0 | K96: Accept: O
A97: A Next-Generation Augmented Reality Platform for Mass Casualty Incidents (MCI) | B97: =IF(COUNTIF('Erin Accepted'!B:B, TRIM(SUBSTITUTE(A97, " ", ""))) > 0, "Accept", "Reject") -> Reject | C97: Reject | D97: =B97=C97 -> TRUE | F97: Came to consensus | K97: Reject: X
A98: Research on the application of AR in the safety inspection of opening and closing stations | B98: =IF(COUNTIF('Erin Accepted'!B:B, TRIM(SUBSTITUTE(A98, " ", ""))) > 0, "Accept", "Reject") -> Reject | C98: Reject | D98: =B98=C98 -> TRUE | F98: Came to consensus
A99: Blaze Buster Augmented Reality Usability Evaluation | B99: =IF(COUNTIF('Erin Accepted'!B:B, TRIM(SUBSTITUTE(A99, " ", ""))) > 0, "Accept", "Reject") -> Reject | C99: Reject | D99: =B99=C99 -> TRUE | E99: Training Interface | F99: Came to consensus
A100: Tangible Immersive Trauma Simulation: Is Mixed Reality the next Level of Medical Skills Training? | B100: =IF(COUNTIF('Erin Accepted'!B:B, TRIM(SUBSTITUTE(A100, " ", ""))) > 0, "Accept", "Reject") -> Reject | C100: Reject | D100: =B100=C100 -> TRUE | E100: Training Interface | F100: Came to consensus
A101: Eliciting Requirements for a Multisensory EXtended Reality Platform for Training and Informal Learning | B101: =IF(COUNTIF('Erin Accepted'!B:B, TRIM(SUBSTITUTE(A101, " ", ""))) > 0, "Accept", "Reject") -> Reject | C101: Reject | D101: =B101=C101 -> TRUE | E101: Training Interface but also not relevant | F101: Came to consensus
A102: Anywhere Projected AR for Robot Communication: A Mid-Air Fog Screen-Robot System | B102: =IF(COUNTIF('Erin Accepted'!B:B, TRIM(SUBSTITUTE(A102, " ", ""))) > 0, "Accept", "Reject") -> Reject | C102: Reject | D102: =B102=C102 -> TRUE | F102: Came to consensus
...

Sheet Table for Paper
A1: Ref | B1: Title | C1: Authors | D1: Year | E1: Visual Output | F1: Auditory Output | G1: Haptic Output | H1: OST HMD | I1: VST HMD | J1: HMD (Unspecified) | K1: Mobile Device | L1: Other Display | M1: Field | N1: Control Room | O1: Training | P1: Others | Q1: EMS | R1: Firefighter | S1: Law Enforcement | T1: Other Discipline | U1: Physiological | V1: Patient/Suspect | W1: Environment | X1: Context Unaware | Y1: Spatial Context | Z1: HUD Context | AA1: Unreported Context | AB1: Interface Elements | AC1: Country | AD1: Conducted User Study? | AE1: Supports Use | AF1: Score??????????? | AG1: Data Collected | AH1: Notes
A2: \cite{antevski_5g-based_2021} | B2: A 5G-Based eHealth Monitoring and Emergency Response System: Experience and Lessons Learned | C2: Antevski et al. | D2: 2021 | E2: x | H2: x | M2: x | Q2: x | U2: x | W2: x | Y2: x | AB2: Points of Interest, Vitals Monitor | AC2: Italy | AD2: No
A3: \cite{arif_comparative_2019} | B3: A Comparative Study of Rendering Devices for Safety-Critical Applications in Operative Control Rooms | C3: Arif et al. | D3: 2019 | E3: x | H3: x | N3: x | R3: x | X3: x | Z3: x | AB3: 2D Map, Annotations | AC3: Austria, France, Spain, Slovakia | AD3: Yes | AE3: No | AF3: 0 | AG3: Usability, Preference
A4: \cite{azpiroz2024white} | B4: White Paper on Adaptive Situational Awareness Enhancing Augmented Reality Interface Design on First Responders in Rescue Tasks | C4: Azpiroz et al. | D4: 2024 | E4: x | H4: x | M4: x | R4: x | U4: x | W4: x | Z4: x | AB4: Radar, Augmented Enhancement | AC4: USA | AD4: No
A5: \cite{schmorrow_implementing_2016} | B5: Implementing user-centered methods and virtual reality to rapidly prototype augmented reality tools for firefighters | C5: Bailie et al. | D5: 2016 | E5: x | F5: x | I5: x | M5: x | R5: x | X5: x | Y5: x | Z5: x | AB5: Breadcrumbs, Navigation Arrow | AC5: USA | AD5: No
A6: \cite{balfour_what_2013} | B6: The what, why and how of achieving urban telepresence | C6: Balfour and Donnelly | D6: 2013 | E6: x | J6: x | L6: x | N6: x | Q6: x | R6: x | S6: x | X6: x | Y6: x | Z6: x | AB6: Augmented Enhancement | AC6: Germany | AD6: No
A7: \cite{berndt_optical_2015} | B7: Optical head-mounted displays in mass casualty incidents: Keeping an eye onpatients and hazardous materials | C7: Berndt et al. | D7: 2015 | E7: x | H7: x | M7: x | Q7: x | W7: x | Z7: x | AB7: Alert, Augmented Support | AC7: United Kingdom | AD7: No
A8: \cite{bhattarai_embedded_2020} | B8: An embedded deep learning system for augmented reality in firefighting applications | C8: Bhattarai et al. | D8: 2020 | E8: x | H8: x | M8: x | R8: x | W8: x | Y8: x | AB8: Object Highlighting | AC8: Brazil | AD8: No
A9: \cite{bram-larbi_collision_2020} | B9: Collision Avoidance Head-Up Display: Design Considerations for Emergency Services’ Vehicles | C9: Bram-Larbi et al. | D9: 2020 | E9: x | L9: x | M9: x | Q9: x | W9: x | Y9: x | AB9: Navigation Arrow | AC9: USA | AD9: No
A10: \cite{brandao_using_2017} | B10: Using augmented reality to improve dismounted operators' situation awareness | C10: Brandao and Pinho | D10: 2017 | E10: x | H10: x | M10: x | S10: x | X10: x | Y10: x | Z10: x | AB10: Navigation Line, Points of Interest, 2D Map, X-Ray, Spatial Reconstruction | AC10: USA | AD10: No
A11: \cite{broach_usability_nodate} | B11: Usability and reliability of smart glasses for secondary triage during mass casualty incidents | C11: Broach et al. | D11: 2018 | E11: x | H11: x | M11: x | Q11: x | X11: x | Z11: x | AB11: Annotations | AC11: Portugal | AD11: Yes | AE11: Yes | AF11: 1 | AG11: Usability, Reliability
A12: \cite{cai_mobile_2023} | B12: Mobile Incident Command Dashboard (MIS-D) | C12: Cai and Siegel | D12: 2023 | E12: x | H12: x | I12: x | K12: x | M12: x | Q12: x | R12: x | S12: x | W12: x | Y12: x | AB12: 3D Map, 2D Map, Points of Interest | AC12: Korea | AD12: No
A13: \cite{campos_mobile_2019} | B13: Mobile Augmented Reality Techniques for Emergency Response | C13: Campos et al. | D13: 2019 | E13: x | K13: x | M13: x | Q13: x | R13: x | S13: x | W13: x | Y13: x | Z13: x | AB13: Points of Interest, 2D Map, Radar | AC13: Greece | AD13: Yes | AE13: Yes | AF13: 1 | AG13: Usability
A14: \cite{chae_design_2023} | B14: Design of a Mixed Reality System for Simulating Indoor Disaster Rescue | C14: Chae et al. | D14: 2023 | E14: x | H14: x | M14: x | R14: x | W14: x | Y14: x | Z14: x | AB14: 2D Map, Navigation Arrow, X-Ray, Points of Interest | AC14: Canada | AD14: Yes | AE14: Yes | AF14: 1 | AG14: Time
A15: \cite{chalimas_cross-device_2023} | B15: Cross-Device Augmented Reality Systems for Fire and Rescue based on Thermal Imaging and Live Tracking | C15: Chalimas and Mania | D15: 2023 | E15: x | H15: x | M15: x | R15: x | W15: x | Y15: x | Z15: x | AB15: 2D Map, Navigation Arrow, Compass | AC15: USA | AD15: No
A16: \cite{chan_erwear_2016} | B16: ERWear: Wearable System Design through the Lens of First Responders | C16: Chan et al. | D16: 2016 | E16: x | H16: x | M16: x | Q16: x | R16: x | S16: x | W16: x | Z16: x | AB16: 2D Map, Points of Interest | AC16: China | AD16: No
A17: \cite{cheng_effective_2023} | B17: Effective Navigation for an Emergency Response for Firefighters with Wearable Haptic Displays Design | C17: Cheng et al. | D17: 2023 | E17: x | G17: x | H17: x | M17: x | R17: x | W17: x | Y17: x | Z17: x | AB17: 2D Map, Points of Interest, Annotations, Object Highlighting, Alert | AC17: Not Reported | AD17: No
A18: \cite{christaki_augmented_2022} | B18: Augmented reality points of interest for improved first responder situational awareness | C18: Christaki et al. | D18: 2022 | E18: x | H18: x | M18: x | Q18: x | R18: x | S18: x | X18: x | Y18: x | AB18: 2D Map, Points of Interest, On Demand Menu, Breadcrumbs, Live Video Feed, Navigation Arrow, Augmented Enhancement | AC18: Greece, France | AD18: No | AH18: Field trial conducted, no formal user study
A19: \cite{christian_google_2014} | B19: Google glass for public safety: Leveraging Google Glass for automatic information retrieval and notification by public safety officers in the field | C19: Christian et al. | D19: 2014 | E19: x | H19: x | M19: x | S19: x | V19: x | Z19: x | AB19: Alert | AC19: USA | AD19: No
A20: \cite{chroust2009training} | B20: Training and supporting first responders by mixed reality environments | C20: Chroust et al. | D20: 2009 | E20: x | J20: x | M20: x | Q20: x | R20: x | S20: x | W20: x | Y20: x | AB20: Points of Interest | AC20: Australia | AD20: No
A21: \cite{crowley_ar_2014} | B21: AR Browser for Points of Interest in Disaster Response in UAV Imagery | C21: Crowley et al. | D21: 2014 | E21: x | K21: x | M21: x | Q21: x | R21: x | S21: x | W21: x | Y21: x | Z21: x | AB21: 2D Map, Points of Interest | AC21: USA | AD21: No
A22: \cite{dave_augmenting_2013} | B22: Augmenting situational awareness for first responders using social media as a sensor | C22: Dave et al. | D22: 2013 | E22: x | K22: x | L22: x | M22: x | Q22: x | R22: x | S22: x | W22: x | Y22: x | AB22: Points of Interest | AC22: USA | AD22: No
A23: \cite{davis2002augmented} | B23: Augmented reality and training for airway management procedures | C23: Davis et al. | D23: 2002 | E23: x | J23: x | L23: x | M23: x | Q23: x | W23: x | Y23: x | AB23: X-Ray | AC23: USA | AD23: No
A24: \cite{demirkan_underground_2024} | B24: Underground mine emergency evacuation planning: AR implementation and casestudy | C24: Demirkan et al. | D24: 2024 | E24: x | H24: x | M24: x | Q24: x | R24: x | S24: x | W24: x | Y24: x | AB24: Edge Detection | AC24: USA | AD24: Yes | AE24: Yes | AF24: 1
A25: \cite{dianxi_design_2021} | B25: Design of Intelligent Firefighter Helmet Based on AR Technology | C25: Dianxi et al. | D25: 2021 | E25: x | J25: x | M25: x | R25: x | W25: x | Y25: x | AB25: Edge Detection | AC25: USA | AD25: No
A26: \cite{doswell2020juxtopia} | B26: Juxtopia®CAMMRAD Prepare: A Wearable AI-AR Platform for Clinical Training Emergency First Response Teams | C26: Doswell et al. | D26: 2020 | E26: x | H26: x | O26: x | Q26: x | X26: x | Y26: x | Z26: x | AB26: Augmented Support | AC26: Netherlands | AD26: No | AH26: Focus group only
A27: \cite{engelbrecht_viability_2018} | B27: Viability of Augmented Content for Field Policing | C27: Engelbrecht and Lukosch | D27: 2018 | E27: x | K27: x | M27: x | S27: x | V27: x | W27: x | Y27: x | AB27: Points of Interest, Alert | AC27: USA | AD27: No | AH27: Heuristic evaluation, not rigorously conducted or reported
A28: \cite{del2014red} | B28: Red Cross Triage App Design for Augmented Reality Glasses | C28: Fernández et al. | D28: 2014 | E28: x | H28: x | M28: x | Q28: x | W28: x | Y28: x | AB28: 2D Map, Augmented Support | AC28: Germany | AD28: No | AH28: Not rigorously reported
A29: \cite{follmann2019technical} | B29: Technical support by smart glasses during a mass casualty incident: A randomized controlled simulation trial on technically assisted triage and telemedical app use in disaster medicine | C29: Follmann et al. | D29: 2019 | E29: x | F29: x | H29: x | M29: x | Q29: x | X29: x | Z29: x | AB29: Augmented Support | AC29: USA | AD29: Yes | AE29: Yes Accuracy, No Time | AF29: 0.5 | AG29: Time, Accuracy
A30: \cite{friedman2024prehospital} | B30: Prehospital Pediatric Emergency Training Using Augmented Reality Simulation: A Prospective, Mixed Methods Study | C30: Friedman et al. | D30: 2024 | E30: x | H30: x | O30: x | Q30: x | V30: x | Y30: x | AB30: Augmented Enhancement | AC30: Spain | AD30: Yes | AE30: Yes | AF30: 1 | AG30: Usability
A31: \cite{garcia_health-5g_2023} | B31: Health-5G: A Mixed Reality-Based System for Remote Medical Assistance in Emergency Situations | C31: García et al. | D31: 2023 | E31: x | F31: x | H31: x | M31: x | Q31: x | U31: x | Y31: x | Z31: x | AB31: Vitals Monitor, On Demand Menu, Augmented Enhancement, Augmented Support | AC31: Germany, Spain, France | AD31: No | AH31: System performance analyzed
A32: \cite{garcia2024smart} | B32: Smart Helmet: Combining Sensors, AI, Augmented Reality, and Personal Protection to Enhance First Responders' Situational Awareness | C32: García et al. | D32: 2024 | E32: x | H32: x | M32: x | R32: x | U32: x | W32: x | Y32: x | Z32: x | AB32: Object Highlighting, Augmented Enhancement, Radar | AC32: Greece, Germany, Spain | AD32: Yes | AE32: Yes | AF32: 1 | AG32: Usability, Performance
A33: \cite{gkika_object_2023} | B33: Object detection and augmented reality annotations for increased situational awareness in light smoke conditions | C33: Gkika et al. | D33: 2023 | E33: x | H33: x | M33: x | R33: x | W33: x | Y33: x | AB33: Object Highlighting | AC33: USA | AD33: No | AH33: Not rigorously reported
A34: \cite{grandi_design_2021} | B34: Design and Simulation of Next-Generation Augmented Reality User Interfaces in Virtual Reality | C34: Grandi et al. | D34: 2021 | E34: x | I34: x | M34: x | R34: x | S34: x | W34: x | Y34: x | Z34: x | AB34: On Demand Menu, Augmented Enhancement, Points of Interest, Alert, 2D Map, Navigation Line, X-Ray, Object Highlighting, Annotations | AC34: USA | AD34: No
A35: \cite{grandi_simulating_2020} | B35: Simulating Next-Generation User Interfaces for Law Enforcement Traffic Stops | C35: Grandi et al. | D35: 2020 | E35: x | G35: x | I35: x | M35: x | S35: x | V35: x | W35: x | Y35: x | AB35: Augmented Enhancement, Object Highlighting, On Demand Display, Alert | AC35: Greece | AD35: No
A36: \cite{arregui_augmented_2022} | B36: An Augmented Reality Framework for First Responders: the RESPOND-A project approach | C36: Grigoriou et al. | D36: 2022 | E36: x | H36: x | M36: x | Q36: x | R36: x | S36: x | V36: x | W36: x | Y36: x | Z36: x | AB36: Alert, Annotations, Points of Interest, 2D Map | AC36: Pakistan | AD36: No
A37: \cite{haque_augmented_2020} | B37: Augmented reality based criminal investigation system (ARCRIME) | C37: Haque and Saleem | D37: 2020 | E37: x | F37: x | H37: x | K37: x | M37: x | S37: x | V37: x | W37: x | Y37: x | Z37: x | AB37: Points of Interest, Object Highlighting, Annotations | AC37: USA | AD37: No
A38: \cite{ii_mixed_2020} | B38: Mixed Reality for Post-Disaster Situational Awareness | C38: Howard et al. | D38: 2020 | E38: x | H38: x | M38: x | Q38: x | R38: x | S38: x | W38: x | Y38: x | AB38: Spatial Reconstruction | AC38: USA | AD38: No
A39: \cite{hu2021human} | B39: Human-in-the-Loop Robot-Augmented Intelligent System for Emergency Reconnaissance | C39: Hu et al. | D39: 2021 | E39: x | I39: x | M39: x | Q39: x | R39: x | S39: x | X39: x | Y39: x | AB39: Object Highlighting, Augmented Enhancement, Annotations, Points of Interest | AC39: Not Reported | AD39: Yes | AE39: Yes Time, Yes False Positives, No False Negatives | AF39: 0.5 | AG39: Time, False Positives, False Negatives
A40: \cite{hu_seeing_nodate} | B40: Seeing through Disaster Rubble in 3D with Ground-Penetrating Radar and Interactive Augmented Reality for Urban Search and Rescue | C40: Hu et al. | D40: 2022 | E40: x | H40: x | I40: x | K40: x | M40: x | Q40: x | R40: x | S40: x | W40: x | Y40: x | AB40: Virtual Objects, Augmented Enhancement, Object Highlighting | AC40: Argentina | AD40: No
A41: \cite{ierache_augmented_2016} | B41: Augmented card system based on knowledge for medical emergency assistance | C41: Ierache et al. | D41: 2016 | E41: x | K41: x | M41: x | Q41: x | V41: x | Y41: x | Z41: x | AB41: Augmented Enhancement | AC41: Luxembourg | AD41: No
A42: \cite{ismael_radiological_2023} | B42: Radiological Incident System using Augmented Reality (RISAR) | C42: Ismael et al. | D42: 2023 | E42: x | H42: x | K42: x | M42: x | Q42: x | R42: x | S42: x | X42: x | AA42: x | AB42: 2D Map, Points of Interest | AC42: USA, Canada | AD42: No
A43: \cite{kapalo_comparing_2022} | B43: Comparing Firefighters' Perceived Workload Using 2D vs. 3D Building Plans to Support Emergency Response Preplanning in a Simulated Fire Scenario | C43: Kapolo et al. | D43: 2020 | E43: x | L43: x | M43: x | R43: x | X43: x | Y43: x | AB43: 3D Map | AC43: Greece | AD43: Yes | AE43: Yes | AF43: 0.5 | AG43: Usability
A44: \cite{karakostas_real-time_2024} | B44: A real-time wearable AR system for egocentric vision on the edge | C44: Karakostas et al. | D44: 2024 | E44: x | J44: x | M44: x | S44: x | W44: x | Y44: x | AB44: Object Highlighting, Live Video Feed, Alert | AC44: USA | AD44: Yes | AE44: Yes | AF44: 1 | AG44: SA, Workload, User Experience
A45: \cite{kelley_guiding_2024} | B45: Guiding Gaze: Comparing Cues for Visual Search | C45: Kelley et al. | D45: 2024 | E45: x | H45: x | M45: x | Q45: x | R45: x | S45: x | X45: x | Y45: x | AB45: Gaze Indicators | AC45: Netherlands | AD45: Yes | AE45: Yes | AF45: 1 | AG45: Time, Accuracy
A46: \cite{kim_mobile_2016} | B46: Mobile augmented reality in support of building damage and safety assessment | C46: Kim et al. | D46: 2016 | E46: x | K46: x | M46: x | Q46: x | R46: x | S46: x | W46: x | Y46: x | Z46: x | AB46: 2D Map, Radar, Spatial Reconstructuon | AC46: USA | AD46: No | AH46: Not conducted on interfaces
A47: \cite{koutitas2019virtual} | B47: A Virtual and Augmented Reality Platform for the Training of First Responders of the Ambulance Bus | C47: Koutitas et al. | D47: 2019 | E47: x | H47: x | O47: x | Q47: x | W47: x | Y47: x | AB47: Points of Interest, Augmented Support | AC47: USA | AD47: Yes | AE47: Yes | AF47: 1 | AG47: Time, Errors | AH47: Not rigorously reported
A48: \cite{lackey_new_2016} | B48: New emergency medicine paradigm via augmented telemedicine | C48: Kurillo et al. | D48: 2016 | E48: x | H48: x | M48: x | Q48: x | X48: x | Y48: x | AB48: Annotations | AC48: China, Australia | AD48: No
A49: \cite{li2019fire} | B49: A Fire Reconnaissance Robot Based on SLAM Position, Thermal Imaging Technologies, and AR Display | C49: Li et al. | D49: 2019 | E49: x | H49: x | M49: x | R49: x | W49: x | Z49: x | AB49: 2D Map, Live Video Feed | AC49: Japan, Australia | AD49: No
A50: \cite{lugtenberg_magicbook_2023} | B50: The MagicBook Revisited | C50: Lugtenberg et al. | D50: 2023 | E50: x | J50: x | N50: x | R50: x | X50: x | Y50: x | AB50: 3D Map, Points of Interest | AC50: USA | AD50: Yes | AE50: Yes | AF50: 1 | AG50: Time, Presence
A51: \cite{majumdar_cloud-based_2023} | B51: A cloud-based fire safety system for emergency responders and civic community | C51: Majumdar and Kirkley | D51: 2023 | E51: x | K51: x | P51: x | R51: x | W51: x | Y51: x | AB51: Object Highlighting, 3D Map, 2D Map, Points of Interest | AC51: USA | AD51: No
A52: \cite{mannuru_mobile_2022} | B52: Mobile AR Application for Navigation and Emergency Response | C52: Mannuru et al. | D52: 2022 | E52: x | K52: x | M52: x | T52: x | W52: x | Y52: x | AB52: 2D Map, Points of Interest | AC52: Indonesia | AD52: Yes | AE52: Yes | AF52: 1 | AG52: Usability
A53: \cite{mantoro_pathfinding_2021} | B53: Pathfinding for Disaster Emergency Route Using Sparse A* and Dijkstra Algorithm with Augmented Reality | C53: Mantoro et al. | D53: 2021 | E53: x | J53: x | K53: x | M53: x | T53: x | W53: x | Y53: x | AB53: 2D Map, Points of Interest | AC53: USA | AD53: No
A54: \cite{nalamothu2024leveraging} | B54: Leveraging Augmented Reality for Improved Situational Awareness During UAV-Driven Search and Rescue Missions | C54: Nalamothu et al. | D54: 2024 | E54: x | H54: x | M54: x | R54: x | S54: x | W54: x | Y54: x | AB54: Points of Interest, Augmented Enhancement | AC54: USA | AD54: Yes | AE54: Yes | AF54: 1 | AG54: Time, Distance, SA
A55: \cite{nelson_user-centered_2022} | B55: User-Centered Design and Evaluation of ARTTS: an Augmented Reality Triage Tool Suite for Mass Casualty Incidents | C55: Nelson et al. | D55: 2022 | E55: x | H55: x | M55: x | Q55: x | X55: x | Y55: x | AB55: Augmented Enhancement, On Demand Menu, Annotations | AC55: Norway | AD55: No
A56: \cite{newaz_supporting_2015} | B56: Supporting first responder in-field communication and navigation using head-mounted displays | C56: Newaz et al. | D56: 2015 | E56: x | F56: x | H56: x | M56: x | Q56: x | R56: x | S56: x | W56: x | Z56: x | AB56: 2D Map | AC56: Sweden | AD56: Yes | AE56: Yes | AF56: 0.5 | AG56: Usability, Time
A57: \cite{nilsson_using_2009} | B57: Using AR to support cross-organisational collaboration in dynamic tasks | C57: Nilsson et al. | D57: 2009 | E57: x | I57: x | J57: x | N57: x | Q57: x | R57: x | S57: x | X57: x | Y57: x | AB57: Points of Interest, 2D Map | AC57: Greece | AD57: Yes | AE57: Yes | AF57: 1 | AG57: Time, Collaboration, SA
A58: \cite{schmorrow_mixed-methods_2024} | B58: A Mixed-Methods Approach for the Evaluation of Situational Awareness and User Experience with Augmented Reality Technologies | C58: Ntoa et al. | D58: 2024 | E58: x | J58: x | M58: x | S58: x | W58: x | Y58: x | AB58: Object Highlighting, Live Video Feed, Alert | AC58: Portugal | AD58: Yes | AE58: Yes | AF58: 1 | AG58: Usability, Acceptance, Workload, SA
A59: \cite{nunes2019augmented} | B59: An augmented reality application to support deployed emergency teams | C59: Nunes et al. | D59: 2018 | E59: x | K59: x | M59: x | Q59: x | R59: x | S59: x | W59: x | Y59: x | Z59: x | AB59: Augmented Compass, Points of Interest | AC59: Portugal | AD59: Yes | AE59: Yes | AF59: 1 | AG59: Usability, Errors
A60: \cite{nunes_augmented_2018} | B60: Augmented Reality in Support of Disaster Response | C60: Nunes et al. | D60: 2018 | E60: x | K60: x | L60: x | M60: x | Q60: x | R60: x | S60: x | X60: x | Y60: x | Z60: x | AB60: Points of Interest, Compass, Radar | AC60: USA | AD60: No
A61: \cite{oconnor_augmented_nodate} | B61: Augmented Reality Technology to Facilitate Proficiency in Emergency Medical Procedures | C61: O'Connor et al. | D61: 2023 | E61: x | H61: x | M61: x | Q61: x | X61: x | Z61: x | AB61: Augmented Support | AC61: USA | AD61: Yes | AE61: Yes | AF61: 1 | AG61: Usability
A62: \cite{oconnor_pilot_2024} | B62: A Pilot Randomized Controlled Trial of Augmented Reality Just-in-TimeGuidance for the Performance of Rugged Field Procedures | C62: O'Connor et al. | D62: 2024 | E62: x | H62: x | M62: x | Q62: x | X62: x | Z62: x | AB62: Augmented Support | AC62: Germany, Spain, France | AD62: Yes | AE62: No | AF62: 0 | AG62: Time
A63: \cite{oregui2024augmented} | B63: Augmented Reality Interface for Adverse-Visibility Conditions Validated by First Responders in Rescue Training Scenarios | C63: Oregui et al. | D63: 2024 | E63: x | H63: x | M63: x | R63: x | W63: x | Y63: x | Z63: x | AB63: Radar, Augmented Enhancement, Object Highlighting | AC63: Greece | AD63: No
A64: \cite{pavlopoulos_augmented_nodate} | B64: An augmented reality system for health care provision via telematics support | C64: Pavlopoulos et al. | D64: 1997 | E64: x | J64: x | M64: x | Q64: x | X64: x | Y64: x | AB64: Annotations | AC64: Greece | AD64: No
A65: \cite{peretti_augmented_2022} | B65: Augmented reality training, command and control framework for first responders | C65: Peretti et al. | D65: 2022 | E65: x | H65: x | N65: x | Q65: x | R65: x | S65: x | X65: x | Y65: x | AB65: Points of Interest, Compass, Augmented Support, 2D Map, Annotations | AC65: USA | AD65: Yes | AE65: Yes | AF65: 1 | AG65: Usability
A66: \cite{phillips2020robotic} | B66: A robotic augmented reality virtual window for law enforcement operations | C66: Phillips et al. | D66: 2020 | E66: x | H66: x | M66: x | S66: x | W66: x | Y66: x | AB66: Object Highlighting, X-Ray | AC66: USA | AD66: No
A67: \cite{balfour_next_2012} | B67: Next generation emergency management common operating picture software/systems (COPSS) | C67: R. E. Balfour | D67: 2012 | E67: x | L67: x | M67: x | Q67: x | R67: x | S67: x | X67: x | Y67: x | AB67: Live Video Feed | AC67: Austria | AD67: No
A68: \cite{rainer2009simrad} | B68: SimRad.NBC - Simulation and information system for rescue units at CBRN disasters | C68: Rainer et al. | D68: 2009 | E68: x | J68: x | M68: x | Q68: x | R68: x | S68: x | W68: x | Y68: x | AB68: Annotations, Points of Interest | AC68: USA | AD68: No
A69: \cite{frasson_cpr_2023} | B69: CPR Emergency Assistance Through Mixed Reality Communication | C69: Rebol et al. | D69: 2023 | E69: x | H69: x | M69: x | Q69: x | X69: x | Y69: x | AB69: Augmented Support | AC69: USA | AD69: Yes | AE69: No | AF69: 0 | AG69: Performance, Workload,
A70: \cite{rojas-munoz_evaluation_2020} | B70: Evaluation of an augmented reality platform for austere surgical telementoring: a randomized controlled crossover study in cricothyroidotomies | C70: Rojas-Muñoz et al. | D70: 2020 | E70: x | F70: x | H70: x | M70: x | Q70: x | X70: x | Y70: x | AB70: Annotations | AC70: Germany, Austria | AD70: Yes | AE70: Yes | AF70: 1 | AG70: Performance, Time
A71: \cite{safranoglou2024augmented} | B71: Augmented Reality for Real-time Decision-Making in Flood Emergencies | C71: Safranoglou et al. | D71: 2024 | E71: x | H71: x | M71: x | Q71: x | R71: x | S71: x | W71: x | Y71: x | AB71: Points of Interest, 3D Map, Augmented Enhancement | AC71: Greece | AD71: Yes | AE71: Yes | AF71: 1 | AG71: Usability
A72: \cite{sainidis_single-handed_2021} | B72: Single-handed gesture UAV control and video feed AR visualization for first responders | C72: Sainidis et al. | D72: 2021 | E72: x | H72: x | M72: x | Q72: x | R72: x | S72: x | X72: x | Y72: x | AB72: Augmented Enhancement, Live Video Feed | AC72: Greece | AD72: No
A73: \cite{sampson_ar_2022} | B73: AR Crew Rescue Assistant and AR Passenger Assistant Application for emergency scenarios on large passenger ships | C73: Sampson et al. | D73: 2022 | E73: x | K73: x | M73: x | T73: x | W73: x | Y73: x | Z73: x | AB73: Points of Interest, Navigation Arrow, 2D Map | AC73: Australia | AD73: No
A74: \cite{schlosser_head-worn_displays_2021} | B74: Head-Worn Displays for Emergency Medical Services Staff | C74: Schlosser et al. | D74: 2021 | E74: x | J74: x | M74: x | Q74: x | V74: x | Y74: x | Z74: x | AB74: Vitals Monitor, Annotations | AC74: Australia | AD74: No
A75: \cite{schlosser2024effects} | B75: Effects of Augmented Reality-Based Remote Mentoring on Task Performance andCommunication: A Simulation Study in the Context of Emergency MedicalServices | C75: Schlosser et al. | D75: 2024 | E75: x | F75: x | H75: x | M75: x | Q75: x | X75: x | Y75: x | AB75: Augmented Support | AC75: Germany | AD75: Yes | AE75: No Time, No Accuracy, Yes Workload, Yes Usability | AF75: 0.5 | AG75: Time, Accuracy, Workload, Usability
A76: \cite{sch_3d_nodate} | B76: 3D Building Reconstruction and Thermal Mapping in Fire Brigade Operations | C76: Schönauer et al. | D76: 2013 | E76: x | I76: x | J76: x | M76: x | R76: x | W76: x | Y76: x | AB76: 3D Map | AC76: Italy | AD76: No
A77: \cite{sebillo_training_2016} | B77: Training emergency responders through augmented reality mobile interfaces | C77: Sebillo et al. | D77: 2016 | E77: x | K77: x | M77: x | Q77: x | R77: x | S77: x | W77: x | Y77: x | Z77: x | AB77: 2D Map, Points of Interest, Object Highlighting | AC77: Not Reported
A78: \cite{sharma_situational_2020} | B78: Situational Awareness-based Augmented Reality Instructional (ARI) Module for Building Evacuation | C78: Sharma et al. | D78: 2020 | E78: x | H78: x | K78: x | M78: x | T78: x | W78: x | Y78: x | AB78: 2D Map, 3D Map, Points of Interest, Navigation Arrow | AC78: Chile
A79: \cite{siu_sidebars_2013} | B79: SidebARs: Improving Awareness of off-Screen Elements in Mobile Augmented Reality | C79: Siu and Herskovic | D79: 2013 | E79: x | K79: x | M79: x | Q79: x | R79: x | S79: x | X79: x | Y79: x | Z79: x | AB79: Points of Interest | AC79: Greece
A80: \cite{stefanidi_real-time_2022} | B80: Real-Time Adaptation of Context-Aware Intelligent User Interfaces, for Enhanced Situational Awareness | C80: Stefanidi et al. | D80: 2022 | E80: x | J80: x | M80: x | S80: x | W80: x | Y80: x | AB80: Object Highlighting, Annotations, Icons, Alert | AC80: UK
A81: \cite{stone_mixed_2017} | B81: A 'mixed reality' simulator concept for future Medical Emergency Response Team training | C81: Stone et al. | D81: 2017 | E81: x | F81: x | H81: x | I81: x | N81: x | Q81: x | X81: x | Y81: x | AB81: 3D Map, Points of Interest | AC81: Japan
A82: \cite{tadokoro_robocup-rescue_2000} | B82: RoboCup-Rescue: An international cooperative research project of robotics and AI for the disaster mitigation problem | C82: Tadokoro et al. | D82: 2000 | E82: x | J82: x | M82: x | Q82: x | R82: x | S82: x | W82: x | AA82: x | AB82: 2D Map, Points of Interest, Spatial Reconstruction | AC82: Germany
A83: \cite{tiemann_celidon_2020} | B83: CELIDON: Supporting first responders through 3D AOA-based UWB Ad-hoclocalization | C83: Tiemann et al. | D83: 2020 | E83: x | J83: x | M83: x | Q83: x | R83: x | S83: x | W83: x | Y83: x | Z83: x | AB83: Points of Interest, Navigation Arrow | AC83: Austria
A84: \cite{umlauft_communication_2016} | B84: A communication and multi-sensor solution to support dynamic generation of a situational picture | C84: Umlauft et al. | D84: 2016 | E84: x | H84: x | K84: x | L84: x | M84: x | Q84: x | R84: x | S84: x | U84: x | W84: x | Z84: x | AB84: 2D Map, Points of Interest | AC84: USA
A85: \cite{walker_mixed_2021} | B85: A Mixed Reality Supervision and Telepresence Interface for Outdoor Field Robotics | C85: Walker et al. | D85: 2021 | E85: x | I85: x | M85: x | Q85: x | R85: x | S85: x | X85: x | Y85: x | AB85: 3D Map, Navigation Lines, Points of Interest | AC85: USA
A86: \cite{wang_person--interest_2013} | B86: Person-of-interest detection system using cloud-supported computerized-eyewear | C86: Wang et al. | D86: 2013 | E86: x | H86: x | M86: x | S86: x | V86: x | Y86: x | Z86: x | AB86: Object Highlighting, Alert | AC86: China
A87: \cite{wang_method_2023} | B87: Method and application of information sharing throughout the emergency rescue process based on 5G and AR wearable devices | C87: Wang et al. | D87: 2023 | E87: x | F87: x | H87: x | M87: x | Q87: x | U87: x | V87: x | Y87: x | Z87: x | AB87: Object Highlighting, Annotations | AC87: USA
A88: \cite{weichelt_augmented_2018} | B88: Augmented Reality Farm MAPPER Development: Lessons Learned from an App Designed to Improve Rural Emergency Response | C88: Weichelt et al. | D88: 2018 | E88: x | K88: x | M88: x | R88: x | W88: x | Y88: x | Z88: x | AB88: Points of Interest, Compass | AC88: USA
A89: \cite{whitlock_designing_2019} | B89: Designing for Mobile and Immersive Visual Analytics in the Field | C89: Whitlock et al. | D89: 2019 | E89: x | H89: x | K89: x | M89: x | R89: x | W89: x | Y89: x | AB89: Annotations, 2D Map | AC89: USA
A90: \cite{wilchek2025ajna} | B90: Ajna: A Wearable Shared Perception System for Extreme Sensemaking | C90: Wilchek et al. | D90: 2025 | E90: x | H90: x | M90: x | R90: x | S90: x | W90: x | Y90: x | AB90: Object Highlighting, Points of Interest | AC90: USA
A91: \cite{zhang_exploring_2024} | B91: Exploring the Design Space of Optical See-through AR Head-Mounted Displays toSupport First Responders in the Field | C91: Zhang et al. | D91: 2024 | E91: x | F91: x | H91: x | M91: x | Q91: x | R91: x | S91: x | W91: x | Y91: x | Z91: x | AB91: Navigation Arrow, 2D Map, 3D Map, Object Highlighting, Points of Interest, Alert | AC91: USA
A92: \cite{majumdar_next-generation_2025} | B92: Next-Generation Emergency Operations: Advancing Crisis Response with Drones, Augmented Reality, and Autonomous Vehicles | C92: Majumdar, Swarnamouli and Mallik, Biswadip Basu | D92: 2025 | E92: x | J92: x | M92: x | R92: x | T92: x | W92: x | Y92: x | Z92: x | AB92: Augmented Enhancement, Points of Interest, Alert | AC92: N/A (survey; global examples) | AD92: No
A93: \cite{chukhno_application-driven_2025} | B93: Application-Driven Offloading of XR Mission Critical via Integrated TN/NTN | C93: Chukhno, Olga and Chukhno, Nadezhda and Ometov, Aleksandr and Pizzi, Sara and Araniti, Giuseppe and Molinaro, Antonella | D93: 2025 | E93: x | F93: x | I93: x | J93: x | M93: x | N93: x | R93: x | S93: x | V93: x | W93: x | Y93: x | Z93: x | AB93: 2D Map, 3D Map, Points of Interest, Annotations, Live Video Feed, Alert, X-Ray | AC93: N/A (system-level simulation) | AD93: No
A94: \cite{pooryousef_criminator_2026} | B94: Criminator: An Easy-to-Use XR "crime Animator" for Rapid Reconstruction and Analysis of Dynamic Crime Scenes | C94: Pooryousef, Vahid and Besançon, Lonni and Cordeil, Maxime and Flight, Chris and Ross, Alastair M and Bassed, Richard and Dwyer, Tim | D94: 2026 | E94: x | I94: x | O94: x | P94: x | S94: x | V94: x | W94: x | Y94: x | Z94: x | AB94: Spatial Reconstruction, Virtual Objects, Annotations, On Demand Menu | AC94: Australia | AD94: Yes
A95: \cite{kosoris_testing_2025} | B95: Testing Future Technologies Using Simulations | C95: Kosoris, Nicole and Fain, Brad and Coleman, Maribeth | D95: 2025 | E95: x | I95: x | M95: x | P95: x | S95: x | V95: x | W95: x | Y95: x | Z95: x | AB95: Annotations, Alert, Augmented Enhancement | AC95: USA | AD95: Yes
A96: \cite{quach_augmented_2026} | B96: Augmented Reality Telemonitoring Systems in Emergency Medical Services for Clinical Decision Support: A Qualitative Study Among Key Stakeholders in Prehospital Care | C96: Quach, Brian F. and Dias, Roger D. and Eyre, Andrew J. and Harari, Rayan E. | D96: 2026 | E96: x | J96: x | M96: x | N96: x | Q96: x | U96: x | V96: x | Z96: x | AB96: Vitals Monitor, Annotations, Live Video Feed, Alert, Augmented Support | AC96: USA | AD96: Yes
A97: \cite{zhang_designing_2026} | B97: Designing Hands-Free Technology to Support Real-Time Patient Data Collection and Documentation for Emergency Care Settings | C97: Zhang, Zhan and Bai, Enze and Xu, Yincao and Stepanian, Aram and Park, Sun Young | D97: 2026 | E97: x | J97: x | M97: x | N97: x | Q97: x | U97: x | V97: x | W97: x | Z97: x | AB97: Vitals Monitor, Annotations, Live Video Feed, On Demand Menu, Augmented Support | AC97: USA | AD97: Yes
A98: \cite{xu_wearable_2026} | B98: Wearable Gaze-Brain–Computer Interface Instrumentation for Visual Target Detection During Hands-Occupied Dual-Tasking | C98: Xu, Xiaoying and Zhang, Huayu and Zeng, Hong and Song, Aiguo and Zhang, Wenbin and Chen, Dapeng | D98: 2026 | E98: x | J98: x | M98: x | R98: x | S98: x | W98: x | Y98: x | Z98: x | AB98: Gaze Indicators, Object Highlighting, Points of Interest, Annotations | AC98: China | AD98: Yes
A99: \cite{segal_understanding_2026} | B99: Understanding Cross-Team Communication Through Shared Cognition in EMS to ED Handoffs | C99: Segal, Jonathan Isaac | D99: 2026 | E99: x | F99: x | J99: x | M99: x | P99: x | Q99: x | U99: x | V99: x | Y99: x | Z99: x | AB99: Vitals Monitor, Annotations, Alert, Augmented Support, On Demand Menu | AC99: USA | AD99: Yes
B100: Far-Target Detection System for Outdoor and Indoor Environments | C100: Sangenis, Eudald and Jao, Chi-Shih and Wai, Crystal and Shkel, Andrei M. | E100: x | H100: x | M100: x | N100: x | R100: x | W100: x | Y100: x | AB100: Points of Interest, direction/distance, LLA coordinates | AC100: USA | AD100: Yes
...
